rmepy/__init__.py
rmepy/decorators.py
rmepy/logger.py
rmepy/robot.py
rmepy/robot_connection.py
rmepy/robot_msg_push.py
rmepy/robot_video_stream.py
rmepy/robot_modules/__init__.py
rmepy/robot_modules/__module_template.py
rmepy/robot_modules/basic_ctrl.py
rmepy/robot_modules/blaster.py
rmepy/robot_modules/chassis.py
rmepy/robot_modules/gimbal.py
rmepy-0.1.0.dist-info/LICENSE
rmepy-0.1.0.dist-info/METADATA
rmepy-0.1.0.dist-info/WHEEL
rmepy-0.1.0.dist-info/top_level.txt
rmepy-0.1.0.dist-info/RECORD
