Metadata-Version: 2.1
Name: rmepy
Version: 0.1.0
Summary: A simple python3 interface for DJI Robomaster EP.
Home-page: https://github.com/233a344a455/Rmepy
Author: DeltaZero
Author-email: 233a344a455@gmail.com
License: MIT
Platform: UNKNOWN
Classifier: Development Status :: 3 - Alpha
Classifier: License :: OSI Approved :: MIT License
Classifier: Natural Language :: Chinese (Simplified)
Classifier: Framework :: Robot Framework
Classifier: Framework :: Robot Framework :: Library
Classifier: Programming Language :: Python
Classifier: Programming Language :: Python :: 3
Classifier: Programming Language :: Python :: 3.6
Classifier: Programming Language :: Python :: Implementation :: CPython
Classifier: Programming Language :: Python :: Implementation :: PyPy
Requires-Python: >=3.6.0
Requires-Dist: opencv-python
Requires-Dist: numpy
Requires-Dist: pillow
